LICENSE
MANIFEST.in
README.rst
setup.py
djbootstrap/__init__.py
djbootstrap/models.py
djbootstrap/tests.py
djbootstrap.egg-info/PKG-INFO
djbootstrap.egg-info/SOURCES.txt
djbootstrap.egg-info/dependency_links.txt
djbootstrap.egg-info/not-zip-safe
djbootstrap.egg-info/requires.txt
djbootstrap.egg-info/top_level.txt
djbootstrap/static/djbootstrap/css/bootstrap-theme.css
djbootstrap/static/djbootstrap/css/bootstrap-theme.min.css
djbootstrap/static/djbootstrap/css/bootstrap.css
djbootstrap/static/djbootstrap/css/bootstrap.min.css
djbootstrap/static/djbootstrap/fonts/glyphicons-halflings-regular.eot
djbootstrap/static/djbootstrap/fonts/glyphicons-halflings-regular.svg
djbootstrap/static/djbootstrap/fonts/glyphicons-halflings-regular.ttf
djbootstrap/static/djbootstrap/fonts/glyphicons-halflings-regular.woff
djbootstrap/static/djbootstrap/js/bootstrap.js
djbootstrap/static/djbootstrap/js/bootstrap.min.js
djbootstrap/static/djbootstrap/js/html5shiv-v3.js
djbootstrap/static/djbootstrap/js/jquery-1.10.2.min.js
djbootstrap/static/djbootstrap/js/jquery-1.10.2.min.map
djbootstrap/templates/djbootstrap/base.html
djbootstrap/templates/djbootstrap/bootstrapped_form.html
djbootstrap/templates/djbootstrap/notification_center.html
djbootstrap/templatetags/__init__.py
djbootstrap/templatetags/bootstrap_tags.py