Metadata-Version: 1.1
Name: djbootstrap
Version: 3.0.1
Summary: Kickstart your django app with twitter bootstrap.
Home-page: https://github.com/madisona/djbootstrap
Author: Aaron Madison
Author-email: UNKNOWN
License: UNKNOWN
Platform: UNKNOWN
Classifier: Development Status :: 4 - Beta
Classifier: Environment :: Web Environment
Classifier: Framework :: Django
Classifier: Intended Audience :: Developers
Classifier: License :: OSI Approved :: BSD License
Classifier: Operating System :: OS Independent
Classifier: Programming Language :: Python
Classifier: Topic :: Software Development
Classifier: Topic :: Software Development :: Libraries :: Application Frameworks
